FLABasicTools/__init__.py
FLABasicTools/__main__.py
FLABasicTools/cli.py
FLABasicTools/data_build.py
FLABasicTools/geo_splits.py
FLABasicTools/overlap.py
FLABasicTools-0.1.6.dist-info/LICENSE.txt
FLABasicTools-0.1.6.dist-info/METADATA
FLABasicTools-0.1.6.dist-info/WHEEL
FLABasicTools-0.1.6.dist-info/top_level.txt
FLABasicTools-0.1.6.dist-info/RECORD
