Metadata-Version: 2.1
Name: FLABasicTools
Version: 0.1.6
Summary: Basic tools for redistrict data used in reports
Home-page: 
Author: Robert Edwardes
Author-email: robie@fairlines.org
License: UNKNOWN
Platform: UNKNOWN
Classifier: Development Status :: 4 - Beta
Classifier: License :: OSI Approved :: MIT License
Classifier: Programming Language :: Python :: 3
Classifier: Programming Language :: Python :: 3.6
Classifier: Programming Language :: Python :: 3.7
Classifier: Programming Language :: Python :: 3.8
Classifier: Programming Language :: Python :: 3.9
Classifier: Programming Language :: Python :: 3.10
Classifier: Programming Language :: Python :: 3 :: Only
Requires-Python: >=3.6, <4
License-File: LICENSE.txt
Requires-Dist: pandas
Requires-Dist: bs4
Requires-Dist: wget
Requires-Dist: geopandas
Requires-Dist: shapely
